{
  "kind": "coverage_report",
  "version": "1.0",
  "generatedAt": "2026-02-24T22:49:31.455Z",
  "sources": {
    "buildRequest": true,
    "implementationPlan": true
  },
  "requirements": {
    "total": 2,
    "implemented": 2,
    "items": [
      {
        "id": "REQ-1",
        "summary": "Replace all occurrences of the current email address in the frontend with 'thejuristshyd@gmail.com'. This includes ContactPage.tsx, Footer.tsx, and any other component or page that displays an email address.",
        "status": "implemented",
        "plannedFiles": [
          "frontend/src/pages/ContactPage.tsx",
          "frontend/src/components/Footer.tsx"
        ],
        "matchedFiles": [
          "frontend/src/pages/ContactPage.tsx",
          "frontend/src/components/Footer.tsx"
        ]
      },
      {
        "id": "REQ-2",
        "summary": "Revert the visual theme (color palette, typography, spacing, component styling, and any decorative elements) to match the 42nd draft version of the site. Apply this theme consistently across all pages and components including Header, Footer, HomePage, ContactPage, AboutPage, ServicesPage, and all other visible pages.",
        "status": "implemented",
        "plannedFiles": [
          "frontend/src/index.css",
          "frontend/tailwind.config.js",
          "frontend/src/components/Header.tsx",
          "frontend/src/components/Footer.tsx",
          "frontend/src/pages/HomePage.tsx",
          "frontend/src/pages/ContactPage.tsx",
          "frontend/src/pages/AboutPage.tsx",
          "frontend/src/pages/ServicesPage.tsx",
          "frontend/src/pages/ServiceDetailPage.tsx",
          "frontend/src/pages/JurisdictionPage.tsx",
          "frontend/src/pages/BlogListPage.tsx",
          "frontend/src/pages/BlogDetailPage.tsx",
          "frontend/src/components/ContactForm.tsx"
        ],
        "matchedFiles": [
          "frontend/src/components/Footer.tsx",
          "frontend/src/pages/ContactPage.tsx"
        ]
      }
    ]
  },
  "changedFiles": [
    "build-request.json",
    "feature_evidence.json",
    "frontend-file-summaries.txt",
    "frontend-implementation-plan.json",
    "frontend/src/components/Footer.tsx",
    "frontend/src/pages/ContactPage.tsx",
    "project_state.json",
    "scratch/component-selection.json",
    "spec.md",
    "spec_vs_diff_report.json"
  ]
}